{
    "App name": "New Zealand Topo Maps",
    "App category": [
        "Maps & Navigation"
    ],
    "URL": "https://play.google.com/store/apps/details?id=com.atlogis.nzmaps.free&hl=en_US",
    "App ID": "com.atlogis.nzmaps.free",
    "Average rating": "4.5",
    "Total reviews": "257000",
    "Contains ads": true,
    "In-app purchases": true,
    "Downloads": "100000+",
    "Price": "$0.00",
    "This app may share these data types with third parties": "Personal info, App activity, and App info and performance",
    "No data collected": {},
    "Data is encrypted in transit": null,
    "You can request that data be deleted": null,
    "Data shared": {
        "Personal info": {
            "User IDs": [
                "Advertising or marketing"
            ]
        },
        "App activity": {
            "App interactions": [
                "Advertising or marketing"
            ]
        },
        "App info and performance": {
            "Crash logs": [
                "Advertising or marketing"
            ],
            "Diagnostics": [
                "Advertising or marketing"
            ]
        }
    },
    "Security practices": {
        "Data is encrypted in transit": null,
        "You can request that data be deleted": null
    }
}