{
    "App name": "WestJet",
    "App category": [
        "Travel & Local"
    ],
    "URL": "https://play.google.com/store/apps/details?id=com.westjet&hl=en_US",
    "App ID": "com.westjet",
    "Average rating": "2.1",
    "Total reviews": "806000",
    "Contains ads": false,
    "In-app purchases": false,
    "Downloads": "1000000+",
    "Price": "$0.00",
    "This app may share these data types with third parties": "Personal info, Financial info, and Health and fitness",
    "This app may collect these data types": "Location, Personal info and 5 others",
    "Data is encrypted in transit": null,
    "You can request that data be deleted": null,
    "Data shared": {
        "Personal info": {
            "Name": [
                "App functionality, Fraud prevention, security, and compliance, Personalization, Account management"
            ],
            "Email address": [
                "App functionality, Developer communications, Fraud prevention, security, and compliance, Personalization, Account management"
            ],
            "Address": [
                "Developer communications, Fraud prevention, security, and compliance"
            ],
            "Phone number": [
                "App functionality, Fraud prevention, security, and compliance"
            ],
            "Other info": [
                "App functionality, Fraud prevention, security, and compliance"
            ]
        },
        "Financial info": {
            "User payment info": [
                "App functionality, Fraud prevention, security, and compliance"
            ]
        },
        "Health and fitness": {
            "Health info": [
                "Fraud prevention, security, and compliance"
            ]
        }
    },
    "Data collected": {
        "Location": {
            "Approximate location": [
                "App functionality, Analytics, Personalization"
            ]
        },
        "Personal info": {
            "Name": [
                "App functionality, Developer communications, Personalization, Account management"
            ],
            "Email address": [
                "App functionality, Fraud prevention, security, and compliance, Personalization, Account management"
            ],
            "User IDs": [
                "App functionality, Personalization, Account management"
            ],
            "Address": [
                "App functionality, Fraud prevention, security, and compliance, Account management"
            ],
            "Phone number": [
                "App functionality, Fraud prevention, security, and compliance, Account management"
            ],
            "Other info": [
                "App functionality, Fraud prevention, security, and compliance, Account management"
            ]
        },
        "Financial info": {
            "User payment info": [
                "App functionality, Analytics, Advertising or marketing, Account management"
            ],
            "Purchase history": [
                "App functionality, Analytics, Personalization"
            ]
        },
        "Health and fitness": {
            "Health info": [
                "App functionality, Fraud prevention, security, and compliance"
            ]
        },
        "App activity": {
            "App interactions": [
                "App functionality, Analytics, Personalization"
            ],
            "In-app search history": [
                "App functionality, Analytics, Personalization"
            ]
        },
        "App info and performance": {
            "Crash logs": [
                "Analytics"
            ],
            "Other app performance data": [
                "Analytics"
            ]
        },
        "Device or other IDs": {
            "Device or other IDs": [
                "Analytics"
            ]
        }
    },
    "Security practices": {
        "Data is encrypted in transit": null,
        "You can request that data be deleted": null
    }
}