{
    "App name": "Dungeon VS Gunner",
    "App category": [
        "Action"
    ],
    "URL": "https://play.google.com/store/apps/details?id=com.corecrystalgames.dungeonvsgunner&hl=en_US",
    "App ID": "com.corecrystalgames.dungeonvsgunner",
    "Average rating": "No ratings",
    "Total reviews": "No reviews",
    "Contains ads": true,
    "In-app purchases": true,
    "Downloads": "50000+",
    "Price": "$0.00",
    "This app may share these data types with third parties": "App activity and App info and performance",
    "This app may collect these data types": "Personal info, App activity and 2 others",
    "Data is encrypted in transit": null,
    "You can request that data be deleted": null,
    "Data shared": {
        "App activity": {
            "App interactions": [
                "Analytics"
            ],
            "Installed apps": [
                "Analytics"
            ]
        },
        "App info and performance": {
            "Crash logs": [
                "Analytics"
            ],
            "Diagnostics": [
                "Analytics"
            ]
        }
    },
    "Data collected": {
        "Personal info": {
            "User IDs": [
                "App functionality, Analytics, Account management"
            ]
        },
        "App activity": {
            "App interactions": [
                "Analytics"
            ],
            "Installed apps": [
                "Analytics"
            ]
        },
        "App info and performance": {
            "Crash logs": [
                "Analytics"
            ],
            "Diagnostics": [
                "Analytics"
            ]
        },
        "Device or other IDs": {
            "Device or other IDs": [
                "App functionality, Account management"
            ]
        }
    },
    "Security practices": {
        "Data is encrypted in transit": null,
        "You can request that data be deleted": null
    }
}