{
    "App name": "Polywords - Word Search Game",
    "App category": [
        "Word",
        "Search",
        "Casual",
        "Single player",
        "Realistic",
        "Offline"
    ],
    "URL": "https://play.google.com/store/apps/details?id=word.search.polywords.puzzle&hl=en_US",
    "App ID": "word.search.polywords.puzzle",
    "Average rating": "2.6",
    "Total reviews": "36",
    "Contains ads": true,
    "In-app purchases": false,
    "Downloads": "1000+",
    "Price": "$0.00",
    "This app may share these data types with third parties": "Location, Personal info and 3 others",
    "This app may collect these data types": "Location, Personal info and 4 others",
    "Data is encrypted in transit": null,
    "You can request that data be deleted": null,
    "Data shared": {
        "Location": {
            "Approximate location": [
                "Analytics, Advertising or marketing"
            ]
        },
        "Personal info": {
            "User IDs": [
                "Analytics, Advertising or marketing"
            ]
        },
        "Financial info": {
            "Purchase history": [
                "Analytics"
            ]
        },
        "App activity": {
            "Installed apps": [
                "Analytics, Advertising or marketing"
            ]
        },
        "Device or other IDs": {
            "Device or other IDs": [
                "Analytics, Advertising or marketing"
            ]
        }
    },
    "Data collected": {
        "Location": {
            "Approximate location": [
                "App functionality, Analytics, Advertising or marketing, Personalization"
            ]
        },
        "Personal info": {
            "User IDs": [
                "Analytics, Advertising or marketing"
            ]
        },
        "Financial info": {
            "Purchase history": [
                "Analytics"
            ]
        },
        "App activity": {
            "App interactions": [
                "Analytics"
            ],
            "Installed apps": [
                "Analytics, Advertising or marketing"
            ]
        },
        "App info and performance": {
            "Crash logs": [
                "Analytics"
            ]
        },
        "Device or other IDs": {
            "Device or other IDs": [
                "Analytics, Advertising or marketing"
            ]
        }
    },
    "Security practices": {
        "Data is encrypted in transit": null,
        "You can request that data be deleted": null
    }
}