{
    "App name": "Match 3D - Tile Triple Puzzle",
    "App category": [
        "Puzzle"
    ],
    "URL": "https://play.google.com/store/apps/details?id=infinitejoy.match3d.tilemaster.cube&hl=en_US",
    "App ID": "infinitejoy.match3d.tilemaster.cube",
    "Average rating": "4.2",
    "Total reviews": "499",
    "Contains ads": true,
    "In-app purchases": false,
    "Downloads": "500000+",
    "Price": "$0.00",
    "This app may share these data types with third parties": "Personal info, App activity and 2 others",
    "This app may collect these data types": "Personal info, App activity and 2 others",
    "Data isn\u2019t encrypted": null,
    "Data can\u2019t be deleted": null,
    "Data shared": {
        "Personal info": {
            "User IDs": [
                "Analytics, Advertising or marketing"
            ]
        },
        "App activity": {
            "App interactions": [
                "Analytics, Advertising or marketing"
            ],
            "Installed apps": [
                "Analytics"
            ],
            "Other actions": [
                "Analytics, Advertising or marketing"
            ]
        },
        "App info and performance": {
            "Crash logs": [
                "Analytics"
            ],
            "Diagnostics": [
                "Analytics"
            ],
            "Other app performance data": [
                "Analytics"
            ]
        },
        "Device or other IDs": {
            "Device or other IDs": [
                "Analytics, Advertising or marketing, Fraud prevention, security, and compliance"
            ]
        }
    },
    "Data collected": {
        "Personal info": {
            "User IDs": [
                "Analytics, Advertising or marketing"
            ]
        },
        "App activity": {
            "App interactions": [
                "Analytics, Advertising or marketing"
            ],
            "Installed apps": [
                "Analytics"
            ],
            "Other actions": [
                "Analytics, Advertising or marketing"
            ]
        },
        "App info and performance": {
            "Crash logs": [
                "Analytics"
            ],
            "Diagnostics": [
                "Analytics"
            ],
            "Other app performance data": [
                "Analytics"
            ]
        },
        "Device or other IDs": {
            "Device or other IDs": [
                "Analytics, Advertising or marketing, Fraud prevention, security, and compliance"
            ]
        }
    },
    "Security practices": {
        "Data isn\u2019t encrypted": null,
        "Data can\u2019t be deleted": null
    }
}