{
    "app_info": {
        "App Name": "\u30aa\u30fc\u30d3\u30b9\u30fb\u30ca\u30d3 - \u9ad8\u7cbe\u5ea6\u306a\u63a2\u77e5&\u81ea\u52d5\u66f4\u202a\u65b0\u202c4+",
        "App Category": "Navigation",
        "URL": "https://apps.apple.com/us/app/%E3%82%AA%E3%83%BC%E3%83%93%E3%82%B9-%E3%83%8A%E3%83%93-%E9%AB%98%E7%B2%BE%E5%BA%A6%E3%81%AA%E6%8E%A2%E7%9F%A5-%E8%87%AA%E5%8B%95%E6%9B%B4%E6%96%B0/id1089052141",
        "App ID": 1089052141,
        "Price": "Free",
        "App Rating": 0.0,
        "No. of Ratings": 0,
        "Offers In-App Purchases": false,
        "Age Rating": "4+",
        "Kids": false
    },
    "compact_dict": {
        "No Details Provided": [
            "The developer will be required to provide privacy details when they submit their next app update."
        ]
    },
    "data_linked": {},
    "data_not_linked": {},
    "data_track": {}
}