{
    "app_info": {
        "App Name": "Bubblegum Hero4+",
        "App Category": "Games",
        "URL": "https://apps.apple.com/us/app/bubblegum-hero/id1289663428",
        "App ID": 1289663428,
        "Price": "Free",
        "App Rating": 4.6,
        "No. of Ratings": 16100,
        "Offers In-App Purchases": true,
        "Age Rating": "4+",
        "Kids": false
    },
    "compact_dict": {
        "No Details Provided": [
            "The developer will be required to provide privacy details when they submit their next app update."
        ]
    },
    "data_linked": {},
    "data_not_linked": {},
    "data_track": {}
}