{
    "app_info": {
        "App Name": "Learn Spanish Frase Master4+",
        "App Category": "Education",
        "URL": "https://apps.apple.com/us/app/learn-spanish-frase-master/id1291568753",
        "App ID": 1291568753,
        "Price": "Free",
        "App Rating": 4.4,
        "No. of Ratings": 147,
        "Offers In-App Purchases": true,
        "Age Rating": "4+",
        "Kids": false
    },
    "compact_dict": {
        "Data Used to Track You": [
            "Usage Data"
        ],
        "Data Not Linked to You": [
            "Identifiers",
            "Usage Data",
            "Diagnostics"
        ]
    },
    "data_linked": {},
    "data_not_linked": {
        "Third-Party Advertising": {
            "Identifiers": [
                "Device ID"
            ],
            "Usage Data": [
                "Advertising Data"
            ]
        },
        "Analytics": {
            "Usage Data": [
                "Product Interaction"
            ],
            "Diagnostics": [
                "Crash Data",
                "Performance Data"
            ]
        }
    },
    "data_track": {
        "Usage Data": [
            "Advertising Data"
        ]
    }
}