{
    "app_info": {
        "App Name": "Harvey's4+",
        "App Category": "Food & Drink",
        "URL": "https://apps.apple.com/us/app/harveys/id1312971866",
        "App ID": 1312971866,
        "Price": "Free",
        "App Rating": 4.8,
        "No. of Ratings": 358,
        "Offers In-App Purchases": false,
        "Age Rating": "4+",
        "Kids": false
    },
    "compact_dict": {
        "Data Used to Track You": [
            "Contact Info"
        ],
        "Data Linked to You": [
            "Contact Info",
            "Identifiers",
            "Diagnostics"
        ],
        "Data Not Linked to You": [
            "Financial Info",
            "Location",
            "Usage Data",
            "Diagnostics"
        ]
    },
    "data_linked": {
        "Analytics": {
            "Diagnostics": [
                "Crash Data"
            ]
        },
        "App Functionality": {
            "Contact Info": [
                "Physical Address",
                "Email Address",
                "Name",
                "Phone Number"
            ],
            "Identifiers": [
                "User ID"
            ],
            "Diagnostics": [
                "Crash Data"
            ]
        }
    },
    "data_not_linked": {
        "Analytics": {
            "Usage Data": [
                "Product Interaction"
            ]
        },
        "App Functionality": {
            "Financial Info": [
                "Payment Info"
            ],
            "Location": [
                "Precise Location",
                "Coarse Location"
            ],
            "Usage Data": [
                "Product Interaction"
            ],
            "Diagnostics": [
                "Performance Data"
            ]
        }
    },
    "data_track": {
        "Contact Info": [
            "Email Address"
        ]
    }
}