{
    "app_info": {
        "App Name": "Hotel Hoppa4+",
        "App Category": "Travel",
        "URL": "https://apps.apple.com/us/app/hotel-hoppa/id1331526280",
        "App ID": 1331526280,
        "Price": "Free",
        "App Rating": 4.2,
        "No. of Ratings": 258,
        "Offers In-App Purchases": false,
        "Age Rating": "4+",
        "Kids": false
    },
    "compact_dict": {
        "Data Linked to You": [
            "Location",
            "Contact Info",
            "User Content",
            "Identifiers"
        ]
    },
    "data_linked": {
        "App Functionality": {
            "Location": [
                "Precise Location"
            ],
            "Contact Info": [
                "Email Address",
                "Name",
                "Phone Number"
            ],
            "User Content": [
                "Customer Support"
            ],
            "Identifiers": [
                "Device ID"
            ]
        }
    },
    "data_not_linked": {},
    "data_track": {}
}