{
    "app_info": {
        "App Name": "Boutiquefeel-Online Fashion4+",
        "App Category": "Shopping",
        "URL": "https://apps.apple.com/us/app/boutiquefeel-online-fashion/id1406292272",
        "App ID": 1406292272,
        "Price": "Free",
        "App Rating": 4.7,
        "No. of Ratings": 4600,
        "Offers In-App Purchases": false,
        "Age Rating": "4+",
        "Kids": false
    },
    "compact_dict": {
        "Data Used to Track You": [
            "Usage Data"
        ],
        "Data Linked to You": [
            "Usage Data"
        ]
    },
    "data_linked": {
        "Analytics": {
            "Usage Data": [
                "Product Interaction"
            ]
        }
    },
    "data_not_linked": {},
    "data_track": {
        "Usage Data": [
            "Product Interaction"
        ]
    }
}