{
    "app_info": {
        "App Name": "kegg12+",
        "App Category": "Health & Fitness",
        "URL": "https://apps.apple.com/us/app/kegg/id1462248924",
        "App ID": 1462248924,
        "Price": "Free",
        "App Rating": 4.3,
        "No. of Ratings": 47,
        "Offers In-App Purchases": false,
        "Age Rating": "12+",
        "Kids": false
    },
    "compact_dict": {
        "Data Not Linked to You": [
            "Health & Fitness",
            "Contact Info",
            "Identifiers",
            "Usage Data",
            "Sensitive Info",
            "Diagnostics"
        ]
    },
    "data_linked": {},
    "data_not_linked": {
        "Analytics": {
            "Usage Data": [
                "Product Interaction"
            ]
        },
        "App Functionality": {
            "Contact Info": [
                "Email Address",
                "Name"
            ],
            "Identifiers": [
                "User ID"
            ]
        },
        "Other Purposes": {
            "Health & Fitness": [
                "Health"
            ],
            "Sensitive Info": [
                "Sensitive Info"
            ],
            "Diagnostics": [
                "Crash Data"
            ]
        }
    },
    "data_track": {}
}