{
    "app_info": {
        "App Name": "2023 NCAA Women\u2019s Final Four12+",
        "App Category": "Sports",
        "URL": "https://apps.apple.com/us/app/2023-ncaa-womens-final-four/id1494341287",
        "App ID": 1494341287,
        "Price": "Free",
        "App Rating": 3.2,
        "No. of Ratings": 51,
        "Offers In-App Purchases": false,
        "Age Rating": "12+",
        "Kids": false
    },
    "compact_dict": {
        "Data Linked to You": [
            "Contact Info"
        ],
        "Data Not Linked to You": [
            "Location",
            "User Content",
            "Identifiers",
            "Usage Data",
            "Diagnostics"
        ]
    },
    "data_linked": {
        "App Functionality": {
            "Contact Info": [
                "Email Address",
                "Name",
                "Phone Number"
            ]
        }
    },
    "data_not_linked": {
        "Third-Party Advertising": {
            "Usage Data": [
                "Advertising Data"
            ]
        },
        "Analytics": {
            "Usage Data": [
                "Product Interaction",
                "Advertising Data"
            ],
            "Diagnostics": [
                "Crash Data",
                "Other Diagnostic Data"
            ]
        },
        "App Functionality": {
            "Location": [
                "Precise Location",
                "Coarse Location"
            ],
            "User Content": [
                "Customer Support"
            ],
            "Identifiers": [
                "Device ID"
            ]
        }
    },
    "data_track": {}
}