{
    "app_info": {
        "App Name": "Drumline Break Creator4+",
        "App Category": "Music",
        "URL": "https://apps.apple.com/us/app/drumline-break-creator/id1507832622",
        "App ID": 1507832622,
        "Price": "$2.99",
        "App Rating": 4.2,
        "No. of Ratings": 33,
        "Offers In-App Purchases": false,
        "Age Rating": "4+",
        "Kids": false
    },
    "compact_dict": {
        "No Details Provided": [
            "The developer will be required to provide privacy details when they submit their next app update."
        ]
    },
    "data_linked": {},
    "data_not_linked": {},
    "data_track": {}
}