{
    "app_info": {
        "App Name": "Tie Dye Anything - Fashion Art4+",
        "App Category": "Games",
        "URL": "https://apps.apple.com/us/app/tie-dye-anything-fashion-art/id1529048386",
        "App ID": 1529048386,
        "Price": "Free",
        "App Rating": 2.7,
        "No. of Ratings": 3,
        "Offers In-App Purchases": false,
        "Age Rating": "4+",
        "Kids": false
    },
    "compact_dict": {
        "Data Used to Track You": [
            "Identifiers"
        ],
        "Data Not Linked to You": [
            "Identifiers"
        ]
    },
    "data_linked": {},
    "data_not_linked": {
        "Third-Party Advertising": {
            "Identifiers": [
                "Device ID"
            ]
        }
    },
    "data_track": {
        "Identifiers": [
            "Device ID"
        ]
    }
}