{
    "app_info": {
        "App Name": "Dog Scan - Breed Identifier4+",
        "App Category": "Lifestyle",
        "URL": "https://apps.apple.com/us/app/dog-scan-breed-identifier/id1552382561",
        "App ID": 1552382561,
        "Price": "Free",
        "App Rating": 4.6,
        "No. of Ratings": 937,
        "Offers In-App Purchases": true,
        "Age Rating": "4+",
        "Kids": false
    },
    "compact_dict": {
        "Data Not Linked to You": [
            "Usage Data",
            "Diagnostics"
        ]
    },
    "data_linked": {},
    "data_not_linked": {
        "Analytics": {
            "Usage Data": [
                "Product Interaction"
            ],
            "Diagnostics": [
                "Crash Data"
            ]
        }
    },
    "data_track": {}
}