{
    "app_info": {
        "App Name": "purp - Make new friends12+",
        "App Category": "Social Networking",
        "URL": "https://apps.apple.com/us/app/purp-make-new-friends/id1562883907",
        "App ID": 1562883907,
        "Price": "Free",
        "App Rating": 4.5,
        "No. of Ratings": 9400,
        "Offers In-App Purchases": true,
        "Age Rating": "12+",
        "Kids": false
    },
    "compact_dict": {
        "Data Linked to You": [
            "Contact Info",
            "User Content",
            "Identifiers"
        ],
        "Data Not Linked to You": [
            "Purchases",
            "Usage Data",
            "Diagnostics"
        ]
    },
    "data_linked": {
        "Product Personalization": {
            "Contact Info": [
                "Name"
            ],
            "User Content": [
                "Photos or Videos"
            ]
        },
        "App Functionality": {
            "Contact Info": [
                "Name"
            ],
            "Identifiers": [
                "User ID"
            ]
        }
    },
    "data_not_linked": {
        "Analytics": {
            "Purchases": [
                "Purchase History"
            ],
            "Usage Data": [
                "Product Interaction"
            ],
            "Diagnostics": [
                "Crash Data",
                "Performance Data"
            ]
        },
        "Product Personalization": {
            "Usage Data": [
                "Product Interaction"
            ]
        },
        "App Functionality": {
            "Purchases": [
                "Purchase History"
            ],
            "Diagnostics": [
                "Crash Data",
                "Performance Data"
            ]
        }
    },
    "data_track": {}
}