{
    "app_info": {
        "App Name": "What Is Grace4+",
        "App Category": "Education",
        "URL": "https://apps.apple.com/us/app/what-is-grace/id1596361271",
        "App ID": 1596361271,
        "Price": "Free",
        "App Rating": 4.3,
        "No. of Ratings": 3,
        "Offers In-App Purchases": false,
        "Age Rating": "4+",
        "Kids": false
    },
    "compact_dict": {
        "Data Not Linked to You": [
            "Usage Data",
            "Diagnostics"
        ]
    },
    "data_linked": {},
    "data_not_linked": {
        "Analytics": {
            "Usage Data": [
                "Product Interaction"
            ]
        },
        "App Functionality": {
            "Diagnostics": [
                "Crash Data",
                "Other Diagnostic Data"
            ]
        }
    },
    "data_track": {}
}