{
    "app_info": {
        "App Name": "Flynow - Finan\u00e7as Pessoais4+",
        "App Category": "Finance",
        "URL": "https://apps.apple.com/us/app/flynow-finan%C3%A7as-pessoais/id1611814185",
        "App ID": 1611814185,
        "Price": "Free",
        "App Rating": 0.0,
        "No. of Ratings": 0,
        "Offers In-App Purchases": true,
        "Age Rating": "4+",
        "Kids": false
    },
    "compact_dict": {
        "Data Not Collected": [
            "The developer does not collect any data from this app."
        ]
    },
    "data_linked": {},
    "data_not_linked": {},
    "data_track": {}
}