{
    "app_info": {
        "App Name": "CWDS Bible17+",
        "App Category": "Books",
        "URL": "https://apps.apple.com/us/app/cwds-bible/id1631596204",
        "App ID": 1631596204,
        "Price": "Free",
        "App Rating": 0.0,
        "No. of Ratings": 0,
        "Offers In-App Purchases": true,
        "Age Rating": "17+",
        "Kids": false
    },
    "compact_dict": {
        "Data Linked to You": [
            "Contact Info"
        ],
        "Data Not Linked to You": [
            "Contact Info"
        ]
    },
    "data_linked": {
        "App Functionality": {
            "Contact Info": [
                "Email Address"
            ]
        }
    },
    "data_not_linked": {
        "App Functionality": {
            "Contact Info": [
                "Name"
            ]
        }
    },
    "data_track": {}
}