{
    "app_info": {
        "App Name": "\ub7fd\ud54f - \ubd80\ubd80 \uc18c\ube44\uc2b5\uad00\uc744 \ubc14\uafd4\uc8fc\ub294 \uac00\uacc4\u202a\ubd80\u202c12+",
        "App Category": "Finance",
        "URL": "https://apps.apple.com/us/app/%EB%9F%BD%ED%95%8F-%EB%B6%80%EB%B6%80-%EC%86%8C%EB%B9%84%EC%8A%B5%EA%B4%80%EC%9D%84-%EB%B0%94%EA%BF%94%EC%A3%BC%EB%8A%94-%EA%B0%80%EA%B3%84%EB%B6%80/id1669442795",
        "App ID": 1669442795,
        "Price": "Free",
        "App Rating": 0.0,
        "No. of Ratings": 0,
        "Offers In-App Purchases": false,
        "Age Rating": "12+",
        "Kids": false
    },
    "compact_dict": {
        "Data Linked to You": [
            "Contact Info"
        ],
        "Data Not Linked to You": [
            "User Content",
            "Identifiers",
            "Usage Data",
            "Diagnostics"
        ]
    },
    "data_linked": {
        "App Functionality": {
            "Contact Info": [
                "Email Address",
                "Name",
                "Phone Number"
            ]
        }
    },
    "data_not_linked": {
        "App Functionality": {
            "User Content": [
                "Photos or Videos"
            ],
            "Identifiers": [
                "User ID",
                "Device ID"
            ],
            "Usage Data": [
                "Other Usage Data"
            ],
            "Diagnostics": [
                "Crash Data"
            ]
        }
    },
    "data_track": {}
}