{
    "app_info": {
        "App Name": "Big Red One Lite9+",
        "App Category": "Entertainment",
        "URL": "https://apps.apple.com/us/app/big-red-one-lite/id341459599",
        "App ID": 341459599,
        "Price": "Free",
        "App Rating": 3.8,
        "No. of Ratings": 5,
        "Offers In-App Purchases": false,
        "Age Rating": "9+",
        "Kids": false
    },
    "compact_dict": {
        "Data Not Linked to You": [
            "Identifiers",
            "Usage Data",
            "Diagnostics"
        ]
    },
    "data_linked": {},
    "data_not_linked": {
        "Third-Party Advertising": {
            "Identifiers": [
                "Device ID"
            ],
            "Usage Data": [
                "Advertising Data"
            ]
        },
        "Analytics": {
            "Identifiers": [
                "Device ID"
            ],
            "Usage Data": [
                "Other Usage Data"
            ],
            "Diagnostics": [
                "Crash Data",
                "Performance Data",
                "Other Diagnostic Data"
            ]
        }
    },
    "data_track": {}
}