{
    "app_info": {
        "App Name": "Hit it Rich! Casino Slots Game17+",
        "App Category": "Games",
        "URL": "https://apps.apple.com/us/app/hit-it-rich-casino-slots-game/id694876905",
        "App ID": 694876905,
        "Price": "Free",
        "App Rating": 4.6,
        "No. of Ratings": 166100,
        "Offers In-App Purchases": true,
        "Age Rating": "17+",
        "Kids": false
    },
    "compact_dict": {
        "Data Used to Track You": [
            "Contact Info",
            "Identifiers"
        ],
        "Data Linked to You": [
            "Purchases",
            "Location",
            "Contact Info",
            "Contacts",
            "User Content",
            "Identifiers",
            "Usage Data",
            "Diagnostics"
        ]
    },
    "data_linked": {
        "Developer's Advertising or Marketing": {
            "Contact Info": [
                "Email Address",
                "Name"
            ]
        },
        "Analytics": {
            "Purchases": [
                "Purchase History"
            ],
            "Location": [
                "Coarse Location"
            ],
            "Contact Info": [
                "Email Address",
                "Name"
            ],
            "User Content": [
                "Customer Support"
            ],
            "Identifiers": [
                "User ID"
            ],
            "Usage Data": [
                "Product Interaction"
            ],
            "Diagnostics": [
                "Crash Data",
                "Performance Data"
            ]
        },
        "Product Personalization": {
            "Purchases": [
                "Purchase History"
            ],
            "Location": [
                "Coarse Location"
            ],
            "Contact Info": [
                "Email Address",
                "Name"
            ],
            "Identifiers": [
                "User ID"
            ],
            "Usage Data": [
                "Product Interaction"
            ]
        },
        "App Functionality": {
            "Purchases": [
                "Purchase History"
            ],
            "Location": [
                "Coarse Location"
            ],
            "Contact Info": [
                "Email Address",
                "Name"
            ],
            "Contacts": [
                "Contacts"
            ],
            "Identifiers": [
                "User ID"
            ],
            "Usage Data": [
                "Product Interaction"
            ],
            "Diagnostics": [
                "Crash Data",
                "Performance Data"
            ]
        },
        "Other Purposes": {
            "Identifiers": [
                "Device ID"
            ]
        }
    },
    "data_not_linked": {},
    "data_track": {
        "Contact Info": [
            "Email Address",
            "Name"
        ],
        "Identifiers": [
            "Device ID"
        ]
    }
}