{
    "app_info": {
        "App Name": "\u6fb3\u8993-\u6fb3\u9580\u4e00\u7ad9\u5f0f\u751f\u6d3b\u670d\u52d9\u5e73\u202a\u53f0\u202c4+",
        "App Category": "Food & Drink",
        "URL": "https://apps.apple.com/us/app/%E6%BE%B3%E8%A6%93-%E6%BE%B3%E9%96%80%E4%B8%80%E7%AB%99%E5%BC%8F%E7%94%9F%E6%B4%BB%E6%9C%8D%E5%8B%99%E5%B9%B3%E5%8F%B0/id1104177940",
        "App ID": 1104177940,
        "Price": "Free",
        "App Rating": 3.0,
        "No. of Ratings": 4,
        "Offers In-App Purchases": false,
        "Age Rating": "4+",
        "Kids": false
    },
    "compact_dict": {
        "Data Used to Track You": [
            "Purchases"
        ],
        "Data Linked to You": [
            "Purchases"
        ],
        "Data Not Linked to You": [
            "Identifiers",
            "Diagnostics"
        ]
    },
    "data_linked": {
        "Developer's Advertising or Marketing": {
            "Purchases": [
                "Purchase History"
            ]
        }
    },
    "data_not_linked": {
        "Analytics": {
            "Identifiers": [
                "Device ID"
            ]
        },
        "App Functionality": {
            "Diagnostics": [
                "Crash Data"
            ]
        }
    },
    "data_track": {
        "Purchases": [
            "Purchase History"
        ]
    }
}