{
    "app_info": {
        "App Name": "EWN Mobile4+",
        "App Category": "Productivity",
        "URL": "https://apps.apple.com/us/app/ewn-mobile/id1176538694",
        "App ID": 1176538694,
        "Price": "Free",
        "App Rating": 4.5,
        "No. of Ratings": 11,
        "Offers In-App Purchases": false,
        "Age Rating": "4+",
        "Kids": false
    },
    "compact_dict": {
        "Data Linked to You": [
            "Identifiers",
            "Usage Data"
        ],
        "Data Not Linked to You": [
            "Diagnostics"
        ]
    },
    "data_linked": {
        "Analytics": {
            "Identifiers": [
                "User ID",
                "Device ID"
            ],
            "Usage Data": [
                "Other Usage Data"
            ]
        },
        "Product Personalization": {
            "Identifiers": [
                "User ID"
            ]
        },
        "App Functionality": {
            "Identifiers": [
                "User ID",
                "Device ID"
            ],
            "Usage Data": [
                "Other Usage Data"
            ]
        }
    },
    "data_not_linked": {
        "Analytics": {
            "Diagnostics": [
                "Crash Data",
                "Other Diagnostic Data"
            ]
        }
    },
    "data_track": {}
}