{
    "app_info": {
        "App Name": "EnergyWatch News4+",
        "App Category": "News",
        "URL": "https://apps.apple.com/us/app/energywatch-news/id1176965286",
        "App ID": 1176965286,
        "Price": "Free",
        "App Rating": 0.0,
        "No. of Ratings": 0,
        "Offers In-App Purchases": false,
        "Age Rating": "4+",
        "Kids": false
    },
    "compact_dict": {
        "Data Used to Track You": [
            "Usage Data"
        ],
        "Data Linked to You": [
            "User Content"
        ],
        "Data Not Linked to You": [
            "Identifiers",
            "Usage Data",
            "Diagnostics"
        ]
    },
    "data_linked": {
        "Analytics": {
            "User Content": [
                "Customer Support"
            ]
        },
        "App Functionality": {
            "User Content": [
                "Customer Support"
            ]
        }
    },
    "data_not_linked": {
        "Analytics": {
            "Identifiers": [
                "User ID"
            ],
            "Usage Data": [
                "Product Interaction"
            ]
        },
        "Product Personalization": {
            "Identifiers": [
                "User ID"
            ],
            "Usage Data": [
                "Product Interaction"
            ]
        },
        "App Functionality": {
            "Identifiers": [
                "User ID"
            ],
            "Usage Data": [
                "Product Interaction"
            ],
            "Diagnostics": [
                "Crash Data",
                "Performance Data"
            ]
        }
    },
    "data_track": {
        "Usage Data": [
            "Product Interaction"
        ]
    }
}