{
    "app_info": {
        "App Name": "DIY Anemometer (Wind Meter\u202a)\u202c4+",
        "App Category": "Weather",
        "URL": "https://apps.apple.com/us/app/diy-anemometer-wind-meter/id1313709233",
        "App ID": 1313709233,
        "Price": "Free",
        "App Rating": 4.5,
        "No. of Ratings": 4,
        "Offers In-App Purchases": true,
        "Age Rating": "4+",
        "Kids": false
    },
    "compact_dict": {
        "Data Not Linked to You": [
            "Diagnostics"
        ]
    },
    "data_linked": {},
    "data_not_linked": {
        "App Functionality": {
            "Diagnostics": [
                "Crash Data"
            ]
        }
    },
    "data_track": {}
}