{
    "app_info": {
        "App Name": "Love Burn Miami4+",
        "App Category": "Travel",
        "URL": "https://apps.apple.com/us/app/love-burn-miami/id1448575957",
        "App ID": 1448575957,
        "Price": "Free",
        "App Rating": 5.0,
        "No. of Ratings": 8,
        "Offers In-App Purchases": false,
        "Age Rating": "4+",
        "Kids": false
    },
    "compact_dict": {
        "Data Used to Track You": [
            "Usage Data"
        ],
        "Data Linked to You": [
            "Usage Data"
        ]
    },
    "data_linked": {
        "Third-Party Advertising": {
            "Usage Data": [
                "Advertising Data"
            ]
        },
        "Analytics": {
            "Usage Data": [
                "Advertising Data"
            ]
        },
        "App Functionality": {
            "Usage Data": [
                "Advertising Data"
            ]
        }
    },
    "data_not_linked": {},
    "data_track": {
        "Usage Data": [
            "Advertising Data"
        ]
    }
}