{
    "app_info": {
        "App Name": "VinkleCut Video Editor & Maker9+",
        "App Category": "Photo & Video",
        "URL": "https://apps.apple.com/us/app/vinklecut-video-editor-maker/id1482506020",
        "App ID": 1482506020,
        "Price": "Free",
        "App Rating": 4.3,
        "No. of Ratings": 223,
        "Offers In-App Purchases": true,
        "Age Rating": "9+",
        "Kids": false
    },
    "compact_dict": {
        "Data Not Collected": [
            "The developer does not collect any data from this app."
        ]
    },
    "data_linked": {},
    "data_not_linked": {},
    "data_track": {}
}