{
    "app_info": {
        "App Name": "Fuelio - gas log, MPG4+",
        "App Category": "Productivity",
        "URL": "https://apps.apple.com/us/app/fuelio-gas-log-mpg/id1487753318",
        "App ID": 1487753318,
        "Price": "Free",
        "App Rating": 3.0,
        "No. of Ratings": 3,
        "Offers In-App Purchases": false,
        "Age Rating": "4+",
        "Kids": false
    },
    "compact_dict": {
        "Data Not Linked to You": [
            "User Content",
            "Usage Data",
            "Diagnostics"
        ]
    },
    "data_linked": {},
    "data_not_linked": {
        "Analytics": {
            "User Content": [
                "Other User Content"
            ],
            "Usage Data": [
                "Product Interaction"
            ],
            "Diagnostics": [
                "Crash Data",
                "Other Diagnostic Data"
            ]
        },
        "Other Purposes": {
            "User Content": [
                "Other User Content"
            ]
        }
    },
    "data_track": {}
}