{
    "app_info": {
        "App Name": "Pesticide Labels Now\u202a!\u202c12+",
        "App Category": "Reference",
        "URL": "https://apps.apple.com/us/app/pesticide-labels-now/id1488170424",
        "App ID": 1488170424,
        "Price": "Free",
        "App Rating": 0.0,
        "No. of Ratings": 0,
        "Offers In-App Purchases": false,
        "Age Rating": "12+",
        "Kids": false
    },
    "compact_dict": {
        "Data Not Linked to You": [
            "Location",
            "User Content",
            "Usage Data"
        ]
    },
    "data_linked": {},
    "data_not_linked": {
        "Analytics": {
            "Location": [
                "Precise Location"
            ],
            "Usage Data": [
                "Product Interaction"
            ]
        },
        "App Functionality": {
            "User Content": [
                "Customer Support"
            ]
        }
    },
    "data_track": {}
}