{
    "app_info": {
        "App Name": "Combine Operators4+",
        "App Category": "Developer Tools",
        "URL": "https://apps.apple.com/us/app/combine-operators/id1507756027",
        "App ID": 1507756027,
        "Price": "Free",
        "App Rating": 4.9,
        "No. of Ratings": 32,
        "Offers In-App Purchases": false,
        "Age Rating": "4+",
        "Kids": false
    },
    "compact_dict": {
        "Data Not Linked to You": [
            "Contact Info"
        ]
    },
    "data_linked": {},
    "data_not_linked": {
        "Developer's Advertising or Marketing": {
            "Contact Info": [
                "Email Address"
            ]
        }
    },
    "data_track": {}
}