{
    "app_info": {
        "App Name": "Awesome Meal Food Diet Tracker4+",
        "App Category": "Health & Fitness",
        "URL": "https://apps.apple.com/us/app/awesome-meal-food-diet-tracker/id1526077962",
        "App ID": 1526077962,
        "Price": "Free",
        "App Rating": 3.3,
        "No. of Ratings": 7,
        "Offers In-App Purchases": false,
        "Age Rating": "4+",
        "Kids": false
    },
    "compact_dict": {
        "No Details Provided": [
            "The developer will be required to provide privacy details when they submit their next app update."
        ]
    },
    "data_linked": {},
    "data_not_linked": {},
    "data_track": {}
}