{
    "app_info": {
        "App Name": "Little Fin4+",
        "App Category": "Games",
        "URL": "https://apps.apple.com/us/app/little-fin/id1567169912",
        "App ID": 1567169912,
        "Price": "Free",
        "App Rating": 3.0,
        "No. of Ratings": 23,
        "Offers In-App Purchases": true,
        "Age Rating": "4+",
        "Kids": false
    },
    "compact_dict": {
        "Data Used to Track You": [
            "Identifiers"
        ],
        "Data Not Linked to You": [
            "Identifiers"
        ]
    },
    "data_linked": {},
    "data_not_linked": {
        "Third-Party Advertising": {
            "Identifiers": [
                "Device ID"
            ]
        }
    },
    "data_track": {
        "Identifiers": [
            "Device ID"
        ]
    }
}