{
    "app_info": {
        "App Name": "Book Art Pattern Maker4+",
        "App Category": "Graphics & Design",
        "URL": "https://apps.apple.com/us/app/book-art-pattern-maker/id1606277884",
        "App ID": 1606277884,
        "Price": "$9.99",
        "App Rating": 4.0,
        "No. of Ratings": 9,
        "Offers In-App Purchases": true,
        "Age Rating": "4+",
        "Kids": false
    },
    "compact_dict": {
        "Data Not Collected": [
            "The developer does not collect any data from this app."
        ]
    },
    "data_linked": {},
    "data_not_linked": {},
    "data_track": {}
}