{
    "app_info": {
        "App Name": "Baseball Coach Plus HD4+",
        "App Category": "Sports",
        "URL": "https://apps.apple.com/us/app/baseball-coach-plus-hd/id430304801",
        "App ID": 430304801,
        "Price": "$2.99",
        "App Rating": 2.0,
        "No. of Ratings": 2,
        "Offers In-App Purchases": false,
        "Age Rating": "4+",
        "Kids": false
    },
    "compact_dict": {
        "No Details Provided": [
            "The developer will be required to provide privacy details when they submit their next app update."
        ]
    },
    "data_linked": {},
    "data_not_linked": {},
    "data_track": {}
}