{
    "app_info": {
        "App Name": "V1 Pro: Coaching Platform4+",
        "App Category": "Sports",
        "URL": "https://apps.apple.com/us/app/v1-pro-coaching-platform/id506014662",
        "App ID": 506014662,
        "Price": "Free",
        "App Rating": 3.1,
        "No. of Ratings": 40,
        "Offers In-App Purchases": false,
        "Age Rating": "4+",
        "Kids": false
    },
    "compact_dict": {
        "Data Linked to You": [
            "Contact Info",
            "User Content",
            "Identifiers"
        ],
        "Data Not Linked to You": [
            "Identifiers",
            "Usage Data",
            "Diagnostics"
        ]
    },
    "data_linked": {
        "Analytics": {
            "User Content": [
                "Customer Support"
            ]
        },
        "App Functionality": {
            "Contact Info": [
                "Email Address",
                "Name"
            ],
            "User Content": [
                "Photos or Videos",
                "Audio Data",
                "Customer Support"
            ],
            "Identifiers": [
                "User ID"
            ]
        }
    },
    "data_not_linked": {
        "Analytics": {
            "Identifiers": [
                "Device ID"
            ],
            "Usage Data": [
                "Product Interaction"
            ],
            "Diagnostics": [
                "Crash Data"
            ]
        }
    },
    "data_track": {}
}