{
    "app_info": {
        "App Name": "Salsa Steps4+",
        "App Category": "Lifestyle",
        "URL": "https://apps.apple.com/us/app/salsa-steps/id514894356",
        "App ID": 514894356,
        "Price": "Free",
        "App Rating": 2.8,
        "No. of Ratings": 4,
        "Offers In-App Purchases": true,
        "Age Rating": "4+",
        "Kids": false
    },
    "compact_dict": {
        "Data Not Linked to You": [
            "Usage Data",
            "Diagnostics"
        ]
    },
    "data_linked": {},
    "data_not_linked": {
        "Analytics": {
            "Usage Data": [
                "Product Interaction"
            ],
            "Diagnostics": [
                "Crash Data"
            ]
        },
        "App Functionality": {
            "Diagnostics": [
                "Crash Data"
            ]
        }
    },
    "data_track": {}
}