{
    "app_info": {
        "App Name": "NDRoads4+",
        "App Category": "Travel",
        "URL": "https://apps.apple.com/us/app/ndroads/id691414078",
        "App ID": 691414078,
        "Price": "Free",
        "App Rating": 3.6,
        "No. of Ratings": 46,
        "Offers In-App Purchases": false,
        "Age Rating": "4+",
        "Kids": false
    },
    "compact_dict": {
        "Data Not Linked to You": [
            "Location",
            "Usage Data"
        ]
    },
    "data_linked": {},
    "data_not_linked": {
        "Analytics": {
            "Location": [
                "Coarse Location"
            ],
            "Usage Data": [
                "Product Interaction",
                "Other Usage Data"
            ]
        }
    },
    "data_track": {}
}