{
    "app_info": {
        "App Name": "Live Wallpaper and Themes App9+",
        "App Category": "Entertainment",
        "URL": "https://apps.apple.com/us/app/live-wallpaper-and-themes-app/id994411234",
        "App ID": 994411234,
        "Price": "Free",
        "App Rating": 4.5,
        "No. of Ratings": 8900,
        "Offers In-App Purchases": true,
        "Age Rating": "9+",
        "Kids": false
    },
    "compact_dict": {
        "Data Used to Track You": [
            "Identifiers"
        ],
        "Data Not Linked to You": [
            "Identifiers",
            "Usage Data",
            "Diagnostics",
            "Other Data"
        ]
    },
    "data_linked": {},
    "data_not_linked": {
        "Third-Party Advertising": {
            "Usage Data": [
                "Advertising Data"
            ],
            "Other Data": [
                "Other Data Types"
            ]
        },
        "Analytics": {
            "Identifiers": [
                "User ID",
                "Device ID"
            ],
            "Usage Data": [
                "Product Interaction"
            ],
            "Diagnostics": [
                "Crash Data"
            ],
            "Other Data": [
                "Other Data Types"
            ]
        },
        "App Functionality": {
            "Usage Data": [
                "Other Usage Data"
            ],
            "Diagnostics": [
                "Performance Data",
                "Other Diagnostic Data"
            ]
        }
    },
    "data_track": {
        "Identifiers": [
            "User ID",
            "Device ID"
        ]
    }
}